wcovid19/__init__.py
wcovid19/wcd.py
wcovid19_data-0.0.2.dist-info/LICENSE
wcovid19_data-0.0.2.dist-info/METADATA
wcovid19_data-0.0.2.dist-info/WHEEL
wcovid19_data-0.0.2.dist-info/top_level.txt
wcovid19_data-0.0.2.dist-info/RECORD
