Metadata-Version: 2.1
Name: wcovid19-data
Version: 0.0.2
Summary: A package to get latest/dynamic covid-19 numbers across the globe
Home-page: https://github.com/pypa/sampleproject
Author: Kantheti Saket Ram
Author-email: sakethaux1111@gmail.com
License: UNKNOWN
Platform: UNKNOWN
Classifier: Programming Language :: Python :: 3.5
Classifier: License :: OSI Approved :: MIT License
Classifier: Operating System :: OS Independent
Requires-Python: >=3.5
Requires-Dist: requests
Requires-Dist: beautifulsoup4
Requires-Dist: pandas
